COPYING
MANIFEST.in
README.rst
requirements.txt
setup.cfg
setup.py
foliolib/__init__.py
foliolib/__version__.py
foliolib/config.py
foliolib/exceptions.py
foliolib.egg-info/PKG-INFO
foliolib.egg-info/SOURCES.txt
foliolib.egg-info/dependency_links.txt
foliolib.egg-info/entry_points.txt
foliolib.egg-info/requires.txt
foliolib.egg-info/top_level.txt
foliolib/apiBuilder/__init__.py
foliolib/apiBuilder/build_api.py
foliolib/apiBuilder/cli.py
foliolib/apiBuilder/oas/__init__.py
foliolib/apiBuilder/oas/baseoas.py
foliolib/apiBuilder/oas/helper.py
foliolib/apiBuilder/oas/oaSchema.py
foliolib/apiBuilder/oas/oaSchemaMethod.py
foliolib/apiBuilder/oas/oaSchemaPath.py
foliolib/apiBuilder/oas/operationIds.py
foliolib/apiBuilder/raml/__init__.py
foliolib/apiBuilder/raml/codeBuilder.py
foliolib/apiBuilder/raml/exceptions.py
foliolib/apiBuilder/raml/helper.py
foliolib/apiBuilder/raml/names.py
foliolib/apiBuilder/raml/ramlMethod.py
foliolib/apiBuilder/raml/ramlUrl.py
foliolib/apiBuilder/raml/tpl.py
foliolib/cli/__init__.py
foliolib/cli/confirm.py
foliolib/cli/err_cli.py
foliolib/cli/orderedGroup.py
foliolib/cli/server.py
foliolib/cli/admin/__init__.py
foliolib/cli/admin/module.py
foliolib/cli/admin/okapi.py
foliolib/cli/admin/platform.py
foliolib/cli/admin/tenant.py
foliolib/cli/folio/__init__.py
foliolib/cli/folio/config.py
foliolib/cli/folio/inventory.py
foliolib/cli/folio/user.py
foliolib/folio/__init__.py
foliolib/folio/configImpl.py
foliolib/folio/exceptions.py
foliolib/folio/inventoryImpl.py
foliolib/folio/permissionsImpl.py
foliolib/folio/usersImpl.py
foliolib/folio/api/__init__.py
foliolib/folio/api/audit.py
foliolib/folio/api/authtoken.py
foliolib/folio/api/batchPrint.py
foliolib/folio/api/bulkOperations.py
foliolib/folio/api/calendar.py
foliolib/folio/api/circulation.py
foliolib/folio/api/circulationItem.py
foliolib/folio/api/circulationStorage.py
foliolib/folio/api/configuration.py
foliolib/folio/api/consortia.py
foliolib/folio/api/consortiaKeycloak.py
foliolib/folio/api/copycat.py
foliolib/folio/api/courses.py
foliolib/folio/api/dataExport.py
foliolib/folio/api/dataExportSpring.py
foliolib/folio/api/dataExportWorker.py
foliolib/folio/api/dataImport.py
