Metadata-Version: 2.1
Name: foliolib
Version: 0.3.12a4
Summary: Okapi/Folio Manager and Library
Home-page: https://github.com/tobi-weber/foliolib
Author: Tobias Weber
Author-email: tobi-weber@gmx.de
License: GPL-3.0 License
Classifier: Development Status :: 3 - Alpha
Classifier: Intended Audience :: Developers
Classifier: License :: OSI Approved :: GNU General Public License v3 (GPLv3)
Classifier: Operating System :: OS Independent
Classifier: Programming Language :: Python
Classifier: Programming Language :: Python :: 3.8
Classifier: Programming Language :: Python :: 3.9
Classifier: Programming Language :: Python :: 3.10
Classifier: Programming Language :: Python :: 3.11
License-File: COPYING
